MANIFEST.in
setup.py
reviewboard_db_auth/__init__.py
reviewboard_db_auth/auth_api.py
reviewboard_db_auth/forms.py
reviewboard_db_auth.egg-info/PKG-INFO
reviewboard_db_auth.egg-info/SOURCES.txt
reviewboard_db_auth.egg-info/dependency_links.txt
reviewboard_db_auth.egg-info/entry_points.txt
reviewboard_db_auth.egg-info/requires.txt
reviewboard_db_auth.egg-info/top_level.txt