Metadata-Version: 1.0
Name: reviewboard-db-auth
Version: 201204-r1
Summary: Database authentication backend for ReviewBoard
Home-page: https://bitbucket.org/shugelee/reviewboard_db_auth
Author: Shuge Lee
Author-email: shuge.lee@gmail.com
License: UNKNOWN
Platform: UNKNOWN
